pulipy/__init__.py
pulipy/function.py
pulipy-0.0.2.dist-info/METADATA
pulipy-0.0.2.dist-info/WHEEL
pulipy-0.0.2.dist-info/RECORD
